{
    "number": "44",
    "title": "O God, We Have Heard",
    "verses": [
        {
            "verse": 2,
            "text": "They gained not the land by the sword of their might; Nor by their own arm were they saved in the fights, But ‘twas by the pow’r of your wonderful grace; Your right hand, your arm, and the light of your face. The Complete Book of Psalms for Singing, 1991; alt."
        },
        {
            "verse": 3,
            "text": "O God, you alone are my God and my king, Now give your command; Jacob’s victory bring. Through you we will surely put down all our foes, And crush in your name all who rise to oppose. The Complete Book of Psalms for Singing, 1991; alt."
        },
        {
            "verse": 4,
            "text": "No trust will I place in my sword or my bow, For you are my Savior from hater and foe. In God we will boast, For you put them to shame, All day and forever we praise your great name. The Complete Book of Psalms for Singing, 1991; alt."
        }
    ],
    "refrain": null,
    "copyright": []
}