{
    "number": "269",
    "title": "The People That in Darkness Sat",
    "verses": [
        {
            "verse": 1,
            "text": "The people that in darkness sat a glorious light have seen; the light has shined on them who long in shades of death have been, in shades of death have been."
        },
        {
            "verse": 2,
            "text": "To hail thee, Sun of Righteousness, the gath'ring nations come; they joy as when the reapers beat their harvest treasures home, their harvest treasures home."
        },
        {
            "verse": 3,
            "text": "For thou their burden dost remove and break the tyrant's rod, as in the day when Midian fell before the sword of God, before the sword of God."
        },
        {
            "verse": 4,
            "text": "To us a Child of hope is born, to us a Son is giv'n, and on his shoulder ever rests all pow'r in earth and heav'n, all pow'r in earth and heav'n."
        },
        {
            "verse": 5,
            "text": "His name shall be the Prince of Peace, the Everlasting Lord, the Wonderful, the Counsellor, the God by all adored, the God by all adored."
        },
        {
            "verse": 6,
            "text": "His righteous government and pow'r shall over all extend; on judgment and on justice based, his reign shall have no end, his reign shall have no end."
        },
        {
            "verse": 7,
            "text": "Lord Jesus, reign in us, we pray, and make us thine alone, who with the Father ever art and Holy Spirit, one; and Holy Spirit, one."
        }
    ],
    "refrain": null,
    "copyright": [
        "Copyright Trinity Psalter Hymnal, 2018, used by permission"
    ]
}