{
    "number": "175",
    "title": "Your Law, O God, Is Our Delight",
    "verses": [
        {
            "verse": 2,
            "text": "Your law, O God, reveals our sin, How foul and stained are we within. O cleanse us from iniquity, and train our hearts from sin to flee."
        },
        {
            "verse": 3,
            "text": "Lord, we have failed your law’s demands With impure hearts and unclean hand. But One has kept them perfectly – Our Savior, Jesus Christ, is he."
        },
        {
            "verse": 4,
            "text": "Our sins were placed upon his head; He suffered anguish in our stead, Now his obedience is our own; Our righteousness is Christ alone."
        },
        {
            "verse": 5,
            "text": "We show our thankfulness and love By keeping precepts from above So teach us Lord, Your statues well; Incline our hearts on them to dwell."
        },
        {
            "verse": 6,
            "text": "Have mercy on your wayward sheep; From us the devil safely keep. Cause us to walk upon your way, And sanctify us more each day."
        },
        {
            "verse": 7,
            "text": "Your law, O God, is our delight; Your statues faithful, true and right. Confirm your word within our hearts That we may not from you depart."
        }
    ],
    "refrain": null,
    "copyright": [
        "Copyright 2016 Derrick and Debbie Vander Meulen"
    ]
}